{
  "sceneId": "dung01_bdg001",
  "levelIdNum": 210,
  "guideHints": [],
  "enemies": [
    {
      "levelLogicId": 21000000001,
      "belongLevelScriptId": 21000000008,
      "entityType": "Enemy",
      "entityDataIdKey": "eny_0051_rodin",
      "defaultHide": true,
      "position": {
        "x": -854.51,
        "y": 142.931,
        "z": 185.38
      },
      "rotation": {
        "x": 0.0,
        "y": 181.56694,
        "z": 0.0
      },
      "scale": {
        "x": 1.0,
        "y": 1.0,
        "z": 1.0
      },
      "forceLoad": false,
      "patrolGait": "Walk",
      "respawnable": true,
      "level": 25,
      "overrideAIConfig": "",
      "enemyGroupId": 0,
      "patrolCfgType": "Patrol"
    },
    {
      "levelLogicId": 21000000002,
      "belongLevelScriptId": 21000000009,
      "entityType": "Enemy",
      "entityDataIdKey": "eny_0051_rodin",
      "defaultHide": true,
      "position": {
        "x": -854.51,
        "y": 142.931,
        "z": 185.38
      },
      "rotation": {
        "x": 0.0,
        "y": 181.56694,
        "z": 0.0
      },
      "scale": {
        "x": 1.0,
        "y": 1.0,
        "z": 1.0
      },
      "forceLoad": false,
      "patrolGait": "Walk",
      "respawnable": true,
      "level": 40,
      "overrideAIConfig": "",
      "enemyGroupId": 0,
      "patrolCfgType": "Patrol"
    },
    {
      "levelLogicId": 21000000004,
      "belongLevelScriptId": 21000000011,
      "entityType": "Enemy",
      "entityDataIdKey": "eny_0051_rodin",
      "defaultHide": true,
      "position": {
        "x": -854.51,
        "y": 142.931,
        "z": 185.38
      },
      "rotation": {
        "x": 0.0,
        "y": 181.56694,
        "z": 0.0
      },
      "scale": {
        "x": 1.0,
        "y": 1.0,
        "z": 1.0
      },
      "forceLoad": false,
      "patrolGait": "Walk",
      "respawnable": true,
      "level": 60,
      "overrideAIConfig": "",
      "enemyGroupId": 0,
      "patrolCfgType": "Patrol"
    }
  ],
  "interactives": [
    {
      "levelLogicId": 21000001578,
      "entityType": "Interactive",
      "entityDataIdKey": "int_fognest_bossfightonly",
      "defaultHide": false,
      "position": {
        "x": -871.67,
        "y": 154.72,
        "z": 163.49
      },
      "rotation": {
        "x": 0.0,
        "y": 0.0,
        "z": 0.0
      },
      "scale": {
        "x": 1.0,
        "y": 1.0,
        "z": 1.0
      },
      "forceLoad": false,
      "isLocked": false,
      "hideInDialog": false,
      "modelScale": 0.0,
      "properties": [],
      "componentProperties": {
        "AbilitySystemForInt": [
          {
            "key": "skill_blackboard",
            "value": {
              "type": "StringList",
              "valueArray": []
            }
          }
        ]
      }
    },
    {
      "levelLogicId": 21000001579,
      "entityType": "Interactive",
      "entityDataIdKey": "int_fognest_bossfightonly",
      "defaultHide": false,
      "position": {
        "x": -833.01,
        "y": 154.72,
        "z": 163.47
      },
      "rotation": {
        "x": 0.0,
        "y": 0.0,
        "z": 0.0
      },
      "scale": {
        "x": 1.0,
        "y": 1.0,
        "z": 1.0
      },
      "forceLoad": false,
      "isLocked": false,
      "hideInDialog": false,
      "modelScale": 0.0,
      "properties": [],
      "componentProperties": {
        "AbilitySystemForInt": [
          {
            "key": "skill_blackboard",
            "value": {
              "type": "StringList",
              "valueArray": []
            }
          }
        ]
      }
    },
    {
      "levelLogicId": 21000001580,
      "entityType": "Interactive",
      "entityDataIdKey": "int_fognest_bossfightonly",
      "defaultHide": false,
      "position": {
        "x": -832.89,
        "y": 154.72,
        "z": 207.15
      },
      "rotation": {
        "x": 0.0,
        "y": 0.0,
        "z": 0.0
      },
      "scale": {
        "x": 1.0,
        "y": 1.0,
        "z": 1.0
      },
      "forceLoad": false,
      "isLocked": false,
      "hideInDialog": false,
      "modelScale": 0.0,
      "properties": [],
      "componentProperties": {
        "AbilitySystemForInt": [
          {
            "key": "skill_blackboard",
            "value": {
              "type": "StringList",
              "valueArray": []
            }
          }
        ]
      }
    },
    {
      "levelLogicId": 21000001581,
      "entityType": "Interactive",
      "entityDataIdKey": "int_fognest_bossfightonly",
      "defaultHide": false,
      "position": {
        "x": -871.9,
        "y": 154.72,
        "z": 207.15
      },
      "rotation": {
        "x": 0.0,
        "y": 0.0,
        "z": 0.0
      },
      "scale": {
        "x": 1.0,
        "y": 1.0,
        "z": 1.0
      },
      "forceLoad": false,
      "isLocked": false,
      "hideInDialog": false,
      "modelScale": 0.0,
      "properties": [],
      "componentProperties": {
        "AbilitySystemForInt": [
          {
            "key": "skill_blackboard",
            "value": {
              "type": "StringList",
              "valueArray": []
            }
          }
        ]
      }
    }
  ],
  "interactiveLockData": [],
  "factoryRegions": [],
  "factoryMines": [],
  "npcs": [],
  "npcClusters": [],
  "levelScripts": [
    {
      "scriptId": 21000000001,
      "allowTick": false,
      "allowStartOnTravelPole": false,
      "startType": "SameWithActive",
      "endType": "SameWithDeactive",
      "exitBufferOverride": true,
      "exitBuffer": 3.0,
      "modules": {},
      "isEmbedded": true,
      "actionMap": {
        "paramBlackboard": {
          "value": []
        },
        "dataMap": {
          "headerList": [
            {
              "$type": "Beyond.Gameplay.Actions.ScriptEvent.OnScriptStart, Gameplay.Beyond",
              "_ID": 0,
              "_nextID": 1,
              "_validate": {
                "constValue": true
              },
              "_uid": "64c08872"
            }
          ],
          "actionList": [
            {
              "$type": "Beyond.Gameplay.Actions.LevelCameraSetParam, Gameplay.Beyond",
              "_ID": 1,
              "_uid": "130ca698",
              "useCurrentScope": true,
              "cameraCtrl": {
                "paramSource": -1,
                "idRef": 2
              },
              "needTween": {
                "constValue": false
              },
              "useHorizontalAngle": {
                "constValue": true
              },
              "useLocalHorizontalAngle": {
                "constValue": false
              },
              "horizontalAngle": {
                "constValue": 0.0
              },
              "useVerticalValue": {
                "constValue": false
              },
              "useZoomScale": {
                "constValue": false
              }
            }
          ],
          "getterList": [
            {
              "$type": "Beyond.Gameplay.Actions.GetCurrentCameraController, Gameplay.Beyond",
              "_ID": 2,
              "_uid": "c997827c"
            }
          ]
        }
      },
      "resetModeWhenActive": "None",
      "resetModeWhenEnd": "None",
      "activeShapeList": [],
      "startShapeList": [],
      "properties": [],
      "propertyIdToKeyMap": {}
    },
    {
      "scriptId": 21000000008,
      "allowTick": false,
      "allowStartOnTravelPole": false,
      "startType": "SameWithActive",
      "endType": "SameWithDeactive",
      "refGameId": "dung01_bossrush01_01",
      "exitBufferOverride": true,
      "exitBuffer": 3.0,
      "modules": {},
      "isEmbedded": true,
      "actionMap": {
        "paramBlackboard": {
          "value": []
        },
        "dataMap": {
          "headerList": [
            {
              "$type": "Beyond.Gameplay.Actions.LevelEvent.OnEntityCastSkill, Gameplay.Beyond",
              "_ID": 7,
              "_nextID": 10,
              "_validate": {
                "constValue": true
              },
              "_uid": "9c2408ed",
              "_entity": {
                "path": "$7@_entity"
              },
              "_entityTemplateId": {
                "path": "$7@_entityTemplateId"
              },
              "_skillId": {
                "path": "$7@_skillId"
              },
              "_firstTargetId": {
                "path": "$7@_firstTargetId"
              },
              "_isCharacter": {
                "constValue": false
              },
              "_skillTypeFilter": {
                "constValue": "None"
              }
            }
          ],
          "actionList": [
            {
              "$type": "Beyond.Gameplay.Actions.CheckBoolIfTrue, Gameplay.Beyond",
              "_ID": 10,
              "_nextID": 11,
              "_uid": "0c944fc0",
              "useCurrentScope": true,
              "_value": {
                "paramSource": -1,
                "constValue": false,
                "idRef": 9
              }
            },
            {
              "$type": "Beyond.Gameplay.Actions.Split, Gameplay.Beyond",
              "_ID": 11,
              "_uid": "fe1f391e",
              "_idList": [
                12,
                18
              ]
            },
            {
              "$type": "Beyond.Gameplay.Actions.WaitForSeconds, Gameplay.Beyond",
              "_ID": 12,
              "_nextID": 13,
              "_uid": "a3b19c22",
              "useCurrentScope": true,
              "_seconds": {
                "constValue": 0.2
              }
            },
            {
              "$type": "Beyond.Gameplay.Actions.PlayCutsceneAction, Gameplay.Beyond",
              "_ID": 18,
              "_nextID": 19,
              "_uid": "a5675276",
              "useCurrentScope": true,
              "_shouldWaitForFinish": {
                "constValue": true
              },
              "_cutsceneId": {
                "constValue": "cutscene_e1m8_2"
              },
              "_existingInteractives": {
                "constValue": []
              },
              "_existingEnemy": {
                "constValue": []
              }
            },
            {
              "$type": "Beyond.Gameplay.Actions.ShowSceneDecorationNew, Gameplay.Beyond",
              "_ID": 13,
              "_nextID": 14,
              "_uid": "eda7e50d",
              "useCurrentScope": true,
              "_sceneName": {
                "constValue": "map01_lv002_art"
              },
              "_groupName": {
                "constValue": "BossLight1"
              },
              "_visible": {
                "constValue": false
              }
            },
            {
              "$type": "Beyond.Gameplay.Actions.EntityCastSkill, Gameplay.Beyond",
              "_ID": 19,
              "_nextID": 20,
              "_uid": "b34d8cd9",
              "useCurrentScope": true,
              "_entity": {
                "constValue": {
                  "logicId": 21000000001
                }
              },
              "_skillId": {
                "constValue": "eny_0051_rodin_changemodel"
              },
              "_targetType": {
                "constValue": "None"
              },
              "_result": {
                "path": "$19@_result"
              }
            },
            {
              "$type": "Beyond.Gameplay.Actions.ShowSceneDecorationNew, Gameplay.Beyond",
              "_ID": 14,
              "_nextID": 15,
              "_uid": "f0c900db",
              "useCurrentScope": true,
              "_sceneName": {
                "constValue": "map01_lv002_art"
              },
              "_groupName": {
                "constValue": "BossLight2"
              },
              "_visible": {
                "constValue": true
              }
            },
            {
              "$type": "Beyond.Gameplay.Actions.PlayAudio, Gameplay.Beyond",
              "_ID": 20,
              "_nextID": 21,
              "_uid": "bdfa5f08",
              "useCurrentScope": true,
              "_key": {
                "constValue": "au_music_combat_boss_state2"
              },
              "_audioPlayingId": {
                "path": "$20@_audioPlayingId"
              }
            },
            {
              "$type": "Beyond.Gameplay.Actions.SetEntitiesVisibility, Gameplay.Beyond",
              "_ID": 15,
              "_nextID": 16,
              "_uid": "5d50d65f",
              "useCurrentScope": true,
              "_targetEntities": {
                "constValue": [
                  {
                    "logicId": 21000000001
                  }
                ]
              },
              "_visibleSource": {
                "constValue": "Common"
              },
              "_isVisible": {
                "constValue": false
              },
              "_resetVisible": {
                "constValue": false
              }
            },
            {
              "$type": "Beyond.Gameplay.Actions.CallServer, Gameplay.Beyond",
              "_ID": 21,
              "_uid": "7781b6ed",
              "useCurrentScope": true,
              "_eventName": {
                "constValue": "#7781b6ed"
              },
              "_eventArgsPtr": {
                "constValue": {
                  "key": "event_args"
                }
              }
            },
            {
              "$type": "Beyond.Gameplay.Actions.SetEntityPosition, Gameplay.Beyond",
              "_ID": 16,
              "_nextID": 17,
              "_uid": "a2967e65",
              "useCurrentScope": true,
              "_target": {
                "constValue": {
                  "logicId": 21000000001
                }
              },
              "_position": {
                "constValue": {
                  "x": -854.41,
                  "y": 142.93,
                  "z": 187.59
                }
              }
            },
            {
              "$type": "Beyond.Gameplay.Actions.SetEntityEulerAngles, Gameplay.Beyond",
              "_ID": 17,
              "_uid": "9296ca8f",
              "useCurrentScope": true,
              "_target": {
                "constValue": {
                  "logicId": 21000000001
                }
              },
              "_eulerAngles": {
                "constValue": {
                  "x": 0.0,
                  "y": 181.5669,
                  "z": 0.0
                }
              }
            }
          ],
          "getterList": [
            {
              "$type": "Beyond.Gameplay.Actions.BoolGetterAnd, Gameplay.Beyond",
              "_ID": 9,
              "_uid": "b796abc4",
              "_valueA": {
                "paramSource": -1,
                "constValue": false,
                "idRef": 24
              },
              "_valueB": {
                "paramSource": -1,
                "constValue": false,
                "idRef": 8
              }
            },
            {
              "$type": "Beyond.Gameplay.Actions.BoolGetterMultOr, Gameplay.Beyond",
              "_ID": 24,
              "_uid": "6880f1ee",
              "_list": [
                {
                  "paramSource": -1,
                  "constValue": false,
                  "idRef": 23
                }
              ]
            },
            {
              "$type": "Beyond.Gameplay.Actions.StringEqual, Gameplay.Beyond",
              "_ID": 8,
              "_uid": "96b0cfdf",
              "_valueA": {
                "paramSource": 100,
                "path": "$7@_skillId"
              },
              "_valueB": {
                "constValue": "eny_0051_rodin_convert"
              }
            },
            {
              "$type": "Beyond.Gameplay.Actions.EntityCompare, Gameplay.Beyond",
              "_ID": 23,
              "_uid": "5101316f",
              "_comparer": {
                "constValue": "Equal"
              },
              "_valueA": {
                "paramSource": 100,
                "path": "$7@_entity",
                "constValue": {
                  "logicId": 0
                }
              },
              "_valueB": {
                "constValue": {
                  "logicId": 21000000001
                }
              }
            },
            {
              "$type": "Beyond.Gameplay.Actions.EntityCompare, Gameplay.Beyond",
              "_ID": 23,
              "_uid": "5101316f",
              "_comparer": {
                "constValue": "Equal"
              },
              "_valueA": {
                "paramSource": 100,
                "path": "$7@_entity",
                "constValue": {
                  "logicId": 0
                }
              },
              "_valueB": {
                "constValue": {
                  "logicId": 21000000001
                }
              }
            }
          ]
        }
      },
      "resetModeWhenActive": "None",
      "resetModeWhenEnd": "None",
      "activeShapeList": [
        {
          "type": "SPHERE",
          "offset": {
            "x": -854.51,
            "y": 142.931,
            "z": 185.38
          },
          "eulerAngles": {
            "x": 0.0,
            "y": 0.0,
            "z": 0.0
          },
          "size": {
            "x": 0.0,
            "y": 0.0,
            "z": 0.0
          },
          "radius": 75.0
        }
      ],
      "startShapeList": [],
      "properties": [
        {
          "key": "lt:p:e2e19bfa:7fffb1b0",
          "value": {
            "type": "Int",
            "valueArray": [
              {
                "valueBit64": 0
              }
            ]
          }
        },
        {
          "key": "lt:mp:e2e19bfa:7fffb1b0",
          "value": {
            "type": "Int",
            "valueArray": [
              {
                "valueBit64": 1
              }
            ]
          }
        }
      ],
      "taskMap": {
        "e2e19bfa": {
          "conditionDict": {
            "7fffb1b0": {
              "isMainObjective": true,
              "objectiveEnum": "Objective1",
              "condition": {
                "$type": "Beyond.Gameplay.CheckMonsterKilled, Gameplay.Beyond",
                "uniqueId": "7fffb1b0",
                "useCurrentScope": false,
                "scopeMask": "Main",
                "useGraphScope": true,
                "_sceneId": {
                  "paramSource": 1000
                },
                "_enemyIds": {
                  "constValue": [
                    {
                      "logicId": 21000000001
                    }
                  ]
                },
                "_comparer": {
                  "constValue": "Equal"
                },
                "_targetValue": {
                  "constValue": 1
                }
              }
            }
          },
          "taskType": "None",
          "needManualCheck": false,
          "canBeTracked": true
        }
      },
      "propertyIdToKeyMap": {
        "1": "lt:p:e2e19bfa:7fffb1b0",
        "1026": "lt:mp:e2e19bfa:7fffb1b0"
      }
    },
    {
      "scriptId": 21000000009,
      "allowTick": false,
      "allowStartOnTravelPole": false,
      "startType": "SameWithActive",
      "endType": "SameWithDeactive",
      "refGameId": "dung01_bossrush01_02",
      "exitBufferOverride": true,
      "exitBuffer": 3.0,
      "modules": {},
      "isEmbedded": true,
      "actionMap": {
        "paramBlackboard": {
          "value": []
        },
        "dataMap": {
          "headerList": [
            {
              "$type": "Beyond.Gameplay.Actions.LevelEvent.OnEntityCastSkill, Gameplay.Beyond",
              "_ID": 7,
              "_nextID": 10,
              "_validate": {
                "constValue": true
              },
              "_uid": "60a59bfe",
              "_entity": {
                "path": "$7@_entity"
              },
              "_entityTemplateId": {
                "path": "$7@_entityTemplateId"
              },
              "_skillId": {
                "path": "$7@_skillId"
              },
              "_firstTargetId": {
                "path": "$7@_firstTargetId"
              },
              "_isCharacter": {
                "constValue": false
              },
              "_skillTypeFilter": {
                "constValue": "None"
              }
            }
          ],
          "actionList": [
            {
              "$type": "Beyond.Gameplay.Actions.CheckBoolIfTrue, Gameplay.Beyond",
              "_ID": 10,
              "_nextID": 11,
              "_uid": "8ca47454",
              "useCurrentScope": true,
              "_value": {
                "paramSource": -1,
                "constValue": false,
                "idRef": 9
              }
            },
            {
              "$type": "Beyond.Gameplay.Actions.Split, Gameplay.Beyond",
              "_ID": 11,
              "_uid": "81265ee3",
              "_idList": [
                12,
                18
              ]
            },
            {
              "$type": "Beyond.Gameplay.Actions.WaitForSeconds, Gameplay.Beyond",
              "_ID": 12,
              "_nextID": 13,
              "_uid": "d76f058c",
              "useCurrentScope": true,
              "_seconds": {
                "constValue": 0.2
              }
            },
            {
              "$type": "Beyond.Gameplay.Actions.PlayCutsceneAction, Gameplay.Beyond",
              "_ID": 18,
              "_nextID": 19,
              "_uid": "c2b5d678",
              "useCurrentScope": true,
              "_shouldWaitForFinish": {
                "constValue": true
              },
              "_cutsceneId": {
                "constValue": "cutscene_e1m8_2"
              },
              "_existingInteractives": {
                "constValue": []
              },
              "_existingEnemy": {
                "constValue": []
              }
            },
            {
              "$type": "Beyond.Gameplay.Actions.ShowSceneDecorationNew, Gameplay.Beyond",
              "_ID": 13,
              "_nextID": 14,
              "_uid": "71083cc0",
              "useCurrentScope": true,
              "_sceneName": {
                "constValue": "map01_lv002_art"
              },
              "_groupName": {
                "constValue": "BossLight1"
              },
              "_visible": {
                "constValue": false
              }
            },
            {
              "$type": "Beyond.Gameplay.Actions.EntityCastSkill, Gameplay.Beyond",
              "_ID": 19,
              "_nextID": 20,
              "_uid": "3d401432",
              "useCurrentScope": true,
              "_entity": {
                "constValue": {
                  "logicId": 21000000002
                }
              },
              "_skillId": {
                "constValue": "eny_0051_rodin_changemodel"
              },
              "_targetType": {
                "constValue": "None"
              },
              "_result": {
                "path": "$19@_result"
              }
            },
            {
              "$type": "Beyond.Gameplay.Actions.ShowSceneDecorationNew, Gameplay.Beyond",
              "_ID": 14,
              "_nextID": 15,
              "_uid": "890b5549",
              "useCurrentScope": true,
              "_sceneName": {
                "constValue": "map01_lv002_art"
              },
              "_groupName": {
                "constValue": "BossLight2"
              },
              "_visible": {
                "constValue": true
              }
            },
            {
              "$type": "Beyond.Gameplay.Actions.PlayAudio, Gameplay.Beyond",
              "_ID": 20,
              "_nextID": 21,
              "_uid": "73e0845d",
              "useCurrentScope": true,
              "_key": {
                "constValue": "au_music_combat_boss_state2"
              },
              "_audioPlayingId": {
                "path": "$20@_audioPlayingId"
              }
            },
            {
              "$type": "Beyond.Gameplay.Actions.SetEntitiesVisibility, Gameplay.Beyond",
              "_ID": 15,
              "_nextID": 16,
              "_uid": "e0ce32f5",
              "useCurrentScope": true,
              "_targetEntities": {
                "constValue": [
                  {
                    "logicId": 21000000002
                  }
                ]
              },
              "_visibleSource": {
                "constValue": "Common"
              },
              "_isVisible": {
                "constValue": false
              },
              "_resetVisible": {
                "constValue": false
              }
            },
            {
              "$type": "Beyond.Gameplay.Actions.CallServer, Gameplay.Beyond",
              "_ID": 21,
              "_uid": "d7f9d0e3",
              "useCurrentScope": true,
              "_eventName": {
                "constValue": "#d7f9d0e3"
              },
              "_eventArgsPtr": {
                "constValue": {
                  "key": "event_args"
                }
              }
            },
            {
              "$type": "Beyond.Gameplay.Actions.SetEntityPosition, Gameplay.Beyond",
              "_ID": 16,
              "_nextID": 17,
              "_uid": "59da1029",
              "useCurrentScope": true,
              "_target": {
                "constValue": {
                  "logicId": 21000000002
                }
              },
              "_position": {
                "constValue": {
                  "x": -854.41,
                  "y": 142.93,
                  "z": 187.59
                }
              }
            },
            {
              "$type": "Beyond.Gameplay.Actions.SetEntityEulerAngles, Gameplay.Beyond",
              "_ID": 17,
              "_uid": "3b7a77d5",
              "useCurrentScope": true,
              "_target": {
                "constValue": {
                  "logicId": 21000000002
                }
              },
              "_eulerAngles": {
                "constValue": {
                  "x": 0.0,
                  "y": 181.5669,
                  "z": 0.0
                }
              }
            }
          ],
          "getterList": [
            {
              "$type": "Beyond.Gameplay.Actions.BoolGetterAnd, Gameplay.Beyond",
              "_ID": 9,
              "_uid": "3dfe3f15",
              "_valueA": {
                "paramSource": -1,
                "constValue": false,
                "idRef": 24
              },
              "_valueB": {
                "paramSource": -1,
                "constValue": false,
                "idRef": 8
              }
            },
            {
              "$type": "Beyond.Gameplay.Actions.BoolGetterMultOr, Gameplay.Beyond",
              "_ID": 24,
              "_uid": "0a1987f2",
              "_list": [
                {
                  "paramSource": -1,
                  "constValue": false,
                  "idRef": 23
                }
              ]
            },
            {
              "$type": "Beyond.Gameplay.Actions.StringEqual, Gameplay.Beyond",
              "_ID": 8,
              "_uid": "e37d9032",
              "_valueA": {
                "paramSource": 100,
                "path": "$7@_skillId"
              },
              "_valueB": {
                "constValue": "eny_0051_rodin_convert"
              }
            },
            {
              "$type": "Beyond.Gameplay.Actions.EntityCompare, Gameplay.Beyond",
              "_ID": 23,
              "_uid": "22c4345e",
              "_comparer": {
                "constValue": "Equal"
              },
              "_valueA": {
                "paramSource": 100,
                "path": "$7@_entity",
                "constValue": {
                  "logicId": 0
                }
              },
              "_valueB": {
                "constValue": {
                  "logicId": 21000000002
                }
              }
            },
            {
              "$type": "Beyond.Gameplay.Actions.EntityCompare, Gameplay.Beyond",
              "_ID": 23,
              "_uid": "22c4345e",
              "_comparer": {
                "constValue": "Equal"
              },
              "_valueA": {
                "paramSource": 100,
                "path": "$7@_entity",
                "constValue": {
                  "logicId": 0
                }
              },
              "_valueB": {
                "constValue": {
                  "logicId": 21000000002
                }
              }
            }
          ]
        }
      },
      "resetModeWhenActive": "None",
      "resetModeWhenEnd": "None",
      "activeShapeList": [
        {
          "type": "SPHERE",
          "offset": {
            "x": -854.51,
            "y": 142.931,
            "z": 185.38
          },
          "eulerAngles": {
            "x": 0.0,
            "y": 0.0,
            "z": 0.0
          },
          "size": {
            "x": 0.0,
            "y": 0.0,
            "z": 0.0
          },
          "radius": 75.0
        }
      ],
      "startShapeList": [],
      "properties": [
        {
          "key": "lt:p:f83b1be5:7fffb1b0",
          "value": {
            "type": "Int",
            "valueArray": [
              {
                "valueBit64": 0
              }
            ]
          }
        },
        {
          "key": "lt:mp:f83b1be5:7fffb1b0",
          "value": {
            "type": "Int",
            "valueArray": [
              {
                "valueBit64": 1
              }
            ]
          }
        }
      ],
      "taskMap": {
        "f83b1be5": {
          "conditionDict": {
            "7fffb1b0": {
              "isMainObjective": true,
              "objectiveEnum": "Objective1",
              "condition": {
                "$type": "Beyond.Gameplay.CheckMonsterKilled, Gameplay.Beyond",
                "uniqueId": "7fffb1b0",
                "useCurrentScope": false,
                "scopeMask": "Main",
                "useGraphScope": true,
                "_sceneId": {
                  "paramSource": 1000
                },
                "_enemyIds": {
                  "constValue": [
                    {
                      "logicId": 21000000002
                    }
                  ]
                },
                "_comparer": {
                  "constValue": "Equal"
                },
                "_targetValue": {
                  "constValue": 1
                }
              }
            }
          },
          "taskType": "None",
          "needManualCheck": false,
          "canBeTracked": true
        }
      },
      "propertyIdToKeyMap": {
        "1": "lt:p:f83b1be5:7fffb1b0",
        "1026": "lt:mp:f83b1be5:7fffb1b0"
      }
    },
    {
      "scriptId": 21000000010,
      "allowTick": false,
      "allowStartOnTravelPole": false,
      "startType": "ByEnterStartShape",
      "endType": "ByExitStartShape",
      "modules": {},
      "isEmbedded": true,
      "actionMap": {
        "paramBlackboard": {
          "value": [
            {
              "key": "skill1done",
              "value": {
                "type": "Bool",
                "valueArray": [
                  {
                    "valueBit64": 0,
                    "valueString": ""
                  }
                ]
              }
            },
            {
              "key": "skill2done",
              "value": {
                "type": "Bool",
                "valueArray": [
                  {
                    "valueBit64": 0,
                    "valueString": ""
                  }
                ]
              }
            },
            {
              "key": "skill3done",
              "value": {
                "type": "Bool",
                "valueArray": [
                  {
                    "valueBit64": 0,
                    "valueString": ""
                  }
                ]
              }
            }
          ]
        },
        "dataMap": {
          "headerList": [
            {
              "$type": "Beyond.Gameplay.Actions.LevelEvent.OnBattleSignal, Gameplay.Beyond",
              "_ID": 0,
              "_nextID": 1,
              "_validate": {
                "constValue": true
              },
              "_uid": "7f88e8b2",
              "_signalId": {
                "constValue": "PlayBgm"
              },
              "_floatValue": {
                "path": "$0@_floatValue"
              }
            },
            {
              "$type": "Beyond.Gameplay.Actions.ScriptEvent.OnScriptStart, Gameplay.Beyond",
              "_ID": 2,
              "_nextID": 3,
              "_validate": {
                "constValue": true
              },
              "_uid": "227e237a"
            },
            {
              "$type": "Beyond.Gameplay.Actions.LevelEvent.OnSpecificEntityDie, Gameplay.Beyond",
              "_ID": 10,
              "_nextID": 11,
              "_validate": {
                "constValue": true
              },
              "_uid": "f466601a",
              "_filterEntity": {
                "constValue": {
                  "logicId": 21000000001
                }
              },
              "_entity": {
                "path": "$10@_entity"
              }
            },
            {
              "$type": "Beyond.Gameplay.Actions.LevelEvent.OnSpecificEntityDie, Gameplay.Beyond",
              "_ID": 12,
              "_nextID": 11,
              "_validate": {
                "constValue": true
              },
              "_uid": "d10499c6",
              "_filterEntity": {
                "constValue": {
                  "logicId": 21000000002
                }
              },
              "_entity": {
                "path": "$12@_entity"
              }
            },
            {
              "$type": "Beyond.Gameplay.Actions.LevelEvent.OnSpecificEntityDie, Gameplay.Beyond",
              "_ID": 13,
              "_nextID": 11,
              "_validate": {
                "constValue": true
              },
              "_uid": "34581498",
              "_filterEntity": {
                "constValue": {
                  "logicId": 21000000004
                }
              },
              "_entity": {
                "path": "$13@_entity"
              }
            }
          ],
          "actionList": [
            {
              "$type": "Beyond.Gameplay.Actions.PlayAudio, Gameplay.Beyond",
              "_ID": 1,
              "_uid": "3c87e96e",
              "useCurrentScope": true,
              "_key": {
                "constValue": "au_music_combat_boss_pre_end"
              },
              "_audioPlayingId": {
                "path": "$1@_audioPlayingId"
              }
            },
            {
              "$type": "Beyond.Gameplay.Actions.PlayAudio, Gameplay.Beyond",
              "_ID": 3,
              "_nextID": 4,
              "_uid": "82de7384",
              "useCurrentScope": true,
              "_key": {
                "constValue": "au_music_combat_boss_002_robin"
              },
              "_audioPlayingId": {
                "path": "$3@_audioPlayingId"
              }
            },
            {
              "$type": "Beyond.Gameplay.Actions.PlayAudio, Gameplay.Beyond",
              "_ID": 4,
              "_nextID": 5,
              "_uid": "23ccdce9",
              "useCurrentScope": true,
              "_key": {
                "constValue": "au_music_combat_boss_state1"
              },
              "_audioPlayingId": {
                "path": "$4@_audioPlayingId"
              }
            },
            {
              "$type": "Beyond.Gameplay.Actions.ShowSceneDecorationNew, Gameplay.Beyond",
              "_ID": 5,
              "_nextID": 6,
              "_uid": "2f1ae52b",
              "useCurrentScope": true,
              "_sceneName": {
                "constValue": "map01_lv002_art"
              },
              "_groupName": {
                "constValue": "BossLight1"
              },
              "_visible": {
                "constValue": true
              }
            },
            {
              "$type": "Beyond.Gameplay.Actions.WaitForSeconds, Gameplay.Beyond",
              "_ID": 6,
              "_nextID": 7,
              "_uid": "49e1ca82",
              "useCurrentScope": true,
              "_seconds": {
                "constValue": 0.5
              }
            },
            {
              "$type": "Beyond.Gameplay.Actions.SetEnemyAIMode, Gameplay.Beyond",
              "_ID": 7,
              "_nextID": 8,
              "_uid": "44f639e7",
              "useCurrentScope": true,
              "_target": {
                "constValue": {
                  "logicId": 21000000001
                }
              },
              "_mode": {
                "constValue": "Battle"
              }
            },
            {
              "$type": "Beyond.Gameplay.Actions.SetEnemyAIMode, Gameplay.Beyond",
              "_ID": 8,
              "_nextID": 9,
              "_uid": "73b5ebdc",
              "useCurrentScope": true,
              "_target": {
                "constValue": {
                  "logicId": 21000000002
                }
              },
              "_mode": {
                "constValue": "Battle"
              }
            },
            {
              "$type": "Beyond.Gameplay.Actions.SetEnemyAIMode, Gameplay.Beyond",
              "_ID": 9,
              "_uid": "62bd3380",
              "useCurrentScope": true,
              "_target": {
                "constValue": {
                  "logicId": 21000000004
                }
              },
              "_mode": {
                "constValue": "Battle"
              }
            },
            {
              "$type": "Beyond.Gameplay.Actions.PlayAudio, Gameplay.Beyond",
              "_ID": 11,
              "_uid": "33c74656",
              "useCurrentScope": true,
              "_key": {
                "constValue": "au_music_combat_boss_win"
              },
              "_audioPlayingId": {
                "path": "$11@_audioPlayingId"
              }
            }
          ],
          "getterList": []
        }
      },
      "resetModeWhenActive": "None",
      "resetModeWhenEnd": "None",
      "activeShapeList": [
        {
          "type": "SPHERE",
          "offset": {
            "x": -855.4427,
            "y": 142.931,
            "z": 182.252869
          },
          "eulerAngles": {
            "x": 0.0,
            "y": 0.0,
            "z": 0.0
          },
          "size": {
            "x": 0.0,
            "y": 0.0,
            "z": 0.0
          },
          "radius": 175.0
        }
      ],
      "startShapeList": [
        {
          "type": "SPHERE",
          "offset": {
            "x": -855.4427,
            "y": 142.931,
            "z": 182.252869
          },
          "eulerAngles": {
            "x": 0.0,
            "y": 0.0,
            "z": 0.0
          },
          "size": {
            "x": 10.0,
            "y": 10.0,
            "z": 10.0
          },
          "radius": 100.0
        }
      ],
      "properties": [],
      "propertyIdToKeyMap": {}
    },
    {
      "scriptId": 21000000011,
      "allowTick": false,
      "allowStartOnTravelPole": false,
      "startType": "SameWithActive",
      "endType": "SameWithDeactive",
      "refGameId": "dung01_bossrush01_03",
      "exitBufferOverride": true,
      "exitBuffer": 3.0,
      "modules": {},
      "isEmbedded": true,
      "actionMap": {
        "paramBlackboard": {
          "value": []
        },
        "dataMap": {
          "headerList": [
            {
              "$type": "Beyond.Gameplay.Actions.LevelEvent.OnEntityCastSkill, Gameplay.Beyond",
              "_ID": 7,
              "_nextID": 10,
              "_validate": {
                "constValue": true
              },
              "_uid": "f105c198",
              "_entity": {
                "path": "$7@_entity"
              },
              "_entityTemplateId": {
                "path": "$7@_entityTemplateId"
              },
              "_skillId": {
                "path": "$7@_skillId"
              },
              "_firstTargetId": {
                "path": "$7@_firstTargetId"
              },
              "_isCharacter": {
                "constValue": false
              },
              "_skillTypeFilter": {
                "constValue": "None"
              }
            }
          ],
          "actionList": [
            {
              "$type": "Beyond.Gameplay.Actions.CheckBoolIfTrue, Gameplay.Beyond",
              "_ID": 10,
              "_nextID": 11,
              "_uid": "2cfe32e6",
              "useCurrentScope": true,
              "_value": {
                "paramSource": -1,
                "constValue": false,
                "idRef": 9
              }
            },
            {
              "$type": "Beyond.Gameplay.Actions.Split, Gameplay.Beyond",
              "_ID": 11,
              "_uid": "06298cbf",
              "_idList": [
                12,
                18
              ]
            },
            {
              "$type": "Beyond.Gameplay.Actions.WaitForSeconds, Gameplay.Beyond",
              "_ID": 12,
              "_nextID": 13,
              "_uid": "e74381ca",
              "useCurrentScope": true,
              "_seconds": {
                "constValue": 0.2
              }
            },
            {
              "$type": "Beyond.Gameplay.Actions.PlayCutsceneAction, Gameplay.Beyond",
              "_ID": 18,
              "_nextID": 19,
              "_uid": "4f3c5aef",
              "useCurrentScope": true,
              "_shouldWaitForFinish": {
                "constValue": true
              },
              "_cutsceneId": {
                "constValue": "cutscene_e1m8_2"
              },
              "_existingInteractives": {
                "constValue": []
              },
              "_existingEnemy": {
                "constValue": []
              }
            },
            {
              "$type": "Beyond.Gameplay.Actions.ShowSceneDecorationNew, Gameplay.Beyond",
              "_ID": 13,
              "_nextID": 14,
              "_uid": "87248bd7",
              "useCurrentScope": true,
              "_sceneName": {
                "constValue": "map01_lv002_art"
              },
              "_groupName": {
                "constValue": "BossLight1"
              },
              "_visible": {
                "constValue": false
              }
            },
            {
              "$type": "Beyond.Gameplay.Actions.EntityCastSkill, Gameplay.Beyond",
              "_ID": 19,
              "_nextID": 20,
              "_uid": "9a2b3d9f",
              "useCurrentScope": true,
              "_entity": {
                "constValue": {
                  "logicId": 21000000004
                }
              },
              "_skillId": {
                "constValue": "eny_0051_rodin_changemodel"
              },
              "_targetType": {
                "constValue": "None"
              },
              "_result": {
                "path": "$19@_result"
              }
            },
            {
              "$type": "Beyond.Gameplay.Actions.ShowSceneDecorationNew, Gameplay.Beyond",
              "_ID": 14,
              "_nextID": 15,
              "_uid": "d3c1dd94",
              "useCurrentScope": true,
              "_sceneName": {
                "constValue": "map01_lv002_art"
              },
              "_groupName": {
                "constValue": "BossLight2"
              },
              "_visible": {
                "constValue": true
              }
            },
            {
              "$type": "Beyond.Gameplay.Actions.PlayAudio, Gameplay.Beyond",
              "_ID": 20,
              "_nextID": 21,
              "_uid": "4df5d3f7",
              "useCurrentScope": true,
              "_key": {
                "constValue": "au_music_combat_boss_state2"
              },
              "_audioPlayingId": {
                "path": "$20@_audioPlayingId"
              }
            },
            {
              "$type": "Beyond.Gameplay.Actions.SetEntitiesVisibility, Gameplay.Beyond",
              "_ID": 15,
              "_nextID": 16,
              "_uid": "3606af0e",
              "useCurrentScope": true,
              "_targetEntities": {
                "constValue": [
                  {
                    "logicId": 21000000004
                  }
                ]
              },
              "_visibleSource": {
                "constValue": "Common"
              },
              "_isVisible": {
                "constValue": false
              },
              "_resetVisible": {
                "constValue": false
              }
            },
            {
              "$type": "Beyond.Gameplay.Actions.CallServer, Gameplay.Beyond",
              "_ID": 21,
              "_uid": "06787458",
              "useCurrentScope": true,
              "_eventName": {
                "constValue": "#06787458"
              },
              "_eventArgsPtr": {
                "constValue": {
                  "key": "event_args"
                }
              }
            },
            {
              "$type": "Beyond.Gameplay.Actions.SetEntityPosition, Gameplay.Beyond",
              "_ID": 16,
              "_nextID": 17,
              "_uid": "bf37515d",
              "useCurrentScope": true,
              "_target": {
                "constValue": {
                  "logicId": 21000000004
                }
              },
              "_position": {
                "constValue": {
                  "x": -854.41,
                  "y": 142.93,
                  "z": 187.59
                }
              }
            },
            {
              "$type": "Beyond.Gameplay.Actions.SetEntityEulerAngles, Gameplay.Beyond",
              "_ID": 17,
              "_uid": "08db5e2c",
              "useCurrentScope": true,
              "_target": {
                "constValue": {
                  "logicId": 21000000004
                }
              },
              "_eulerAngles": {
                "constValue": {
                  "x": 0.0,
                  "y": 181.5669,
                  "z": 0.0
                }
              }
            }
          ],
          "getterList": [
            {
              "$type": "Beyond.Gameplay.Actions.BoolGetterAnd, Gameplay.Beyond",
              "_ID": 9,
              "_uid": "246c9a65",
              "_valueA": {
                "paramSource": -1,
                "constValue": false,
                "idRef": 24
              },
              "_valueB": {
                "paramSource": -1,
                "constValue": false,
                "idRef": 8
              }
            },
            {
              "$type": "Beyond.Gameplay.Actions.BoolGetterMultOr, Gameplay.Beyond",
              "_ID": 24,
              "_uid": "061b3d1c",
              "_list": [
                {
                  "paramSource": -1,
                  "constValue": false,
                  "idRef": 23
                }
              ]
            },
            {
              "$type": "Beyond.Gameplay.Actions.StringEqual, Gameplay.Beyond",
              "_ID": 8,
              "_uid": "dcd517e3",
              "_valueA": {
                "paramSource": 100,
                "path": "$7@_skillId"
              },
              "_valueB": {
                "constValue": "eny_0051_rodin_convert"
              }
            },
            {
              "$type": "Beyond.Gameplay.Actions.EntityCompare, Gameplay.Beyond",
              "_ID": 23,
              "_uid": "5d3c11c2",
              "_comparer": {
                "constValue": "Equal"
              },
              "_valueA": {
                "paramSource": 100,
                "path": "$7@_entity",
                "constValue": {
                  "logicId": 0
                }
              },
              "_valueB": {
                "constValue": {
                  "logicId": 21000000004
                }
              }
            },
            {
              "$type": "Beyond.Gameplay.Actions.EntityCompare, Gameplay.Beyond",
              "_ID": 23,
              "_uid": "5d3c11c2",
              "_comparer": {
                "constValue": "Equal"
              },
              "_valueA": {
                "paramSource": 100,
                "path": "$7@_entity",
                "constValue": {
                  "logicId": 0
                }
              },
              "_valueB": {
                "constValue": {
                  "logicId": 21000000004
                }
              }
            }
          ]
        }
      },
      "resetModeWhenActive": "None",
      "resetModeWhenEnd": "None",
      "activeShapeList": [
        {
          "type": "SPHERE",
          "offset": {
            "x": -854.51,
            "y": 142.931,
            "z": 185.38
          },
          "eulerAngles": {
            "x": 0.0,
            "y": 0.0,
            "z": 0.0
          },
          "size": {
            "x": 0.0,
            "y": 0.0,
            "z": 0.0
          },
          "radius": 75.0
        }
      ],
      "startShapeList": [],
      "properties": [
        {
          "key": "lt:p:d8c39957:7fffb1b0",
          "value": {
            "type": "Int",
            "valueArray": [
              {
                "valueBit64": 0
              }
            ]
          }
        },
        {
          "key": "lt:mp:d8c39957:7fffb1b0",
          "value": {
            "type": "Int",
            "valueArray": [
              {
                "valueBit64": 1
              }
            ]
          }
        }
      ],
      "taskMap": {
        "d8c39957": {
          "conditionDict": {
            "7fffb1b0": {
              "isMainObjective": true,
              "objectiveEnum": "Objective1",
              "condition": {
                "$type": "Beyond.Gameplay.CheckMonsterKilled, Gameplay.Beyond",
                "uniqueId": "7fffb1b0",
                "useCurrentScope": false,
                "scopeMask": "Main",
                "useGraphScope": true,
                "_sceneId": {
                  "paramSource": 1000
                },
                "_enemyIds": {
                  "constValue": [
                    {
                      "logicId": 21000000004
                    }
                  ]
                },
                "_comparer": {
                  "constValue": "Equal"
                },
                "_targetValue": {
                  "constValue": 1
                }
              }
            }
          },
          "taskType": "None",
          "needManualCheck": false,
          "canBeTracked": true
        }
      },
      "propertyIdToKeyMap": {
        "1": "lt:p:d8c39957:7fffb1b0",
        "1026": "lt:mp:d8c39957:7fffb1b0"
      }
    }
  ],
  "patrols": [],
  "npcAttractSets": [],
  "enemyAttractSets": [],
  "missionAreas": [],
  "taskAreas": [],
  "enemyGroup": [],
  "cameraPoses": [],
  "focusPoints": [],
  "splines": [],
  "airWalls": [
    {
      "groupId": 21000000001,
      "defaultOn": true,
      "bounds": {
        "m_center": {
          "x": -852.702759,
          "y": 146.9455,
          "z": 139.663254
        },
        "m_size": {
          "x": 15.8062744,
          "y": 9.0,
          "z": 1.43917847
        }
      },
      "polyLineWalls": [
        {
          "bounds": {
            "m_center": {
              "x": -852.702759,
              "y": 146.9455,
              "z": 139.663254
            },
            "m_size": {
              "x": 14.8062744,
              "y": 8.0,
              "z": 0.439178467
            }
          },
          "posList": [
            {
              "x": -860.1059,
              "y": 139.882843
            },
            {
              "x": -845.2996,
              "y": 139.443665
            },
            {
              "x": -860.1059,
              "y": 139.882843
            }
          ],
          "heightRange": {
            "x": 142.9455,
            "y": 150.9455
          },
          "visualHeightRange": {
            "x": 142.9455,
            "y": 150.9455
          },
          "useQuadTree": false,
          "usage": 2,
          "pushDis": 2.0,
          "pushWarnDis": 5.0,
          "disableDefaultEffect": false
        }
      ],
      "useOctree": false,
      "checkData": {
        "checkType": 0
      }
    },
    {
      "groupId": 21000000002,
      "defaultOn": true,
      "bounds": {
        "m_center": {
          "x": -854.978333,
          "y": 146.9455,
          "z": 218.6515
        },
        "m_size": {
          "x": 81.81494,
          "y": 9.0,
          "z": 1.80999756
        }
      },
      "polyLineWalls": [
        {
          "bounds": {
            "m_center": {
              "x": -854.978333,
              "y": 146.9455,
              "z": 218.6515
            },
            "m_size": {
              "x": 80.81494,
              "y": 8.0,
              "z": 0.809997559
            }
          },
          "posList": [
            {
              "x": -895.3858,
              "y": 218.2465
            },
            {
              "x": -814.570862,
              "y": 219.0565
            },
            {
              "x": -895.3858,
              "y": 218.2465
            }
          ],
          "heightRange": {
            "x": 142.9455,
            "y": 150.9455
          },
          "visualHeightRange": {
            "x": 142.9455,
            "y": 150.9455
          },
          "useQuadTree": false,
          "usage": 2,
          "pushDis": 2.0,
          "pushWarnDis": 5.0,
          "disableDefaultEffect": false
        }
      ],
      "useOctree": false,
      "checkData": {
        "checkType": 0
      }
    }
  ],
  "environmentVolumes": [],
  "spawners": [],
  "worldWayPointSets": [],
  "towerWayPointSets": [],
  "waterVolumes": [],
  "levelUIs": [],
  "aiTransData": [
    {
      "transId": 1,
      "key": "lv002_rodin_centerpoint",
      "position": {
        "x": -854.41,
        "y": 142.93,
        "z": 187.59
      },
      "rotation": {
        "x": 0.0,
        "y": 0.0,
        "z": 0.0
      }
    },
    {
      "transId": 2,
      "key": "lv002_rodin_emitpos1",
      "position": {
        "x": -871.67,
        "y": 154.72,
        "z": 163.49
      },
      "rotation": {
        "x": 0.0,
        "y": 0.0,
        "z": 0.0
      }
    },
    {
      "transId": 3,
      "key": "lv002_rodin_emitpos2",
      "position": {
        "x": -833.01,
        "y": 154.72,
        "z": 163.47
      },
      "rotation": {
        "x": 0.0,
        "y": 0.0,
        "z": 0.0
      }
    },
    {
      "transId": 4,
      "key": "lv002_rodin_emitpos3",
      "position": {
        "x": -832.89,
        "y": 154.72,
        "z": 207.15
      },
      "rotation": {
        "x": 0.0,
        "y": 0.0,
        "z": 0.0
      }
    },
    {
      "transId": 5,
      "key": "lv002_rodin_emitpos4",
      "position": {
        "x": -871.9,
        "y": 154.72,
        "z": 207.15
      },
      "rotation": {
        "x": 0.0,
        "y": 0.0,
        "z": 0.0
      }
    }
  ],
  "attractLists": [],
  "safeZone": {
    "boxes": []
  },
  "factoryPredefineData": {
    "powerGates": []
  },
  "predefinedParams": [],
  "functionArea": {
    "ranges": [],
    "baseData": [],
    "repatriateZoneData": [],
    "cameraVolumeData": [],
    "radioTriggerZoneData": [],
    "cameraLookAtData": [],
    "cameraAddControlStateData": [],
    "ambienceCameraData": [],
    "storySafeZones": [],
    "sceneToast": [],
    "blockAIBarkData": [],
    "isolateEntityZoneData": [],
    "functionAreaConditionData": []
  },
  "doodadGroup": []
}