{
  "m_allParameters": [],
  "type": "Beyond.Gameplay.DialogTree",
  "nodes": [
    {
      "_actorNodeData": {
        "mfTrunkActionData": {
          "exUIDescriptor": {
            "_disableClickTime": 1.0
          },
          "_trunkId": "dlg_e2m7_8_001",
          "useLipSync": true,
          "voiceConfig": {},
          "microExpressionDesc": {},
          "actorIndex": 1,
          "duration": -1.0,
          "actionEnum": 307
        },
        "camActData": {
          "camDescriptor": {
            "modeNum": -1,
            "posName": "3_1_2_1",
            "slotNum": 1,
            "modeId": "1v2_Medium_Shot_S_low",
            "camType": 2,
            "pos": {
              "x": 1.725231,
              "y": 2.096146,
              "z": -4.15027
            },
            "rot": {
              "x": 10.8292,
              "y": 336.4828,
              "z": 359.9931
            },
            "fov": 25.0
          },
          "mCamDescriptor": {
            "modeNum": -1,
            "camType": 2
          },
          "actorIndex": 1,
          "delay": 0.0,
          "actionEnum": 51
        },
        "teleportAllEntityActData": {
          "overrideAllActorPos": true,
          "actorPosList": [
            {
              "pos": {
                "x": -3.904104e-06,
                "z": 2.594785
              },
              "rot": {
                "y": 180.0
              }
            },
            {
              "pos": {
                "x": -0.07129742,
                "z": -0.0004517734
              }
            },
            {
              "pos": {
                "x": -0.770017,
                "z": 0.1299956
              },
              "rot": {
                "y": 28.1
              }
            }
          ]
        },
        "_showNpcs": [],
        "_hideNpcs": [],
        "_actorIndex": 1,
        "animActData": {
          "anim": {
            "fadeIn": 0.2,
            "montageDesc": {
              "montageKeyTag": {
                "tagName": "Montage/NPC/Humanoid/Girl/Pelica/talkrighthand1",
                "tagId": -1725435828
              },
              "montageFadeInTransitionInfo": {
                "bIsFixedTransitionTime": true,
                "fixedTransitionDuration": 0.5
              },
              "montageOverrideEntryTransitionInfo": []
            },
            "maleMontageOverrideDesc": {},
            "animEndType": 1
          },
          "actorIndex": 1
        },
        "emotionActData": {
          "emotionDesc": {
            "browsTrackInfo": {},
            "eyesTrackInfo": {},
            "mouthTrackInfo": {}
          },
          "mEmotionDesc": {
            "browsTrackInfo": {},
            "eyesTrackInfo": {},
            "mouthTrackInfo": {}
          },
          "actorIndex": 1
        },
        "lookAtActData": {
          "lookAtDescriptor": {},
          "actorIndex": 1
        },
        "eyeLookAtActData": {
          "lookAtDescriptor": {},
          "actorIndex": 1
        },
        "turnToActData": {
          "actorIndex": 1
        },
        "actions": [
          {
            "cameraDOFDescriptor": {
              "dofData": {
                "farFocusStart": 7.0,
                "farFocusEnd": 8.0,
                "farRadius": 1.0
              },
              "enable": true
            },
            "$type": "Beyond.Gameplay.DialogCamDOFActionData"
          }
        ],
        "actionGroups": [],
        "$type": "Beyond.Gameplay.DTTrunkNodeData"
      },
      "additionalWidth": 207.0,
      "_position": {
        "x": 191.0,
        "y": 174.0
      },
      "$type": "Beyond.Gameplay.DialogTreeTrunkNode",
      "$id": "0"
    },
    {
      "_actorNodeData": {
        "mfTrunkActionData": {
          "exUIDescriptor": {
            "_disableClickTime": 1.0
          },
          "_trunkId": "dlg_e2m7_8_002",
          "useLipSync": true,
          "voiceConfig": {},
          "microExpressionDesc": {},
          "duration": -1.0,
          "actionEnum": 307
        },
        "camActData": {
          "camDescriptor": {
            "modeNum": 3,
            "posName": "3_1_2_1",
            "modeId": "CameraTransformMode3",
            "pos": {
              "x": 0.94,
              "y": 1.404731,
              "z": 1.64
            },
            "rot": {
              "x": 358.1868,
              "y": 211.0712
            },
            "fov": 14.0
          },
          "mCamDescriptor": {},
          "actorIndex": 0,
          "delay": 0.0,
          "actionEnum": 51
        },
        "teleportAllEntityActData": {
          "actorPosList": []
        },
        "_showNpcs": [],
        "_hideNpcs": [],
        "_actorIndex": 0,
        "animActData": {
          "anim": {
            "fadeIn": 0.2,
            "montageDesc": {
              "montageKeyTag": {
                "tagName": "Montage/NPC/Virtual/wipe",
                "tagId": 634055523
              },
              "montageFadeInTransitionInfo": {
                "bIsFixedTransitionTime": true,
                "fixedTransitionDuration": 0.5
              },
              "montageOverrideEntryTransitionInfo": []
            },
            "maleMontageOverrideDesc": {},
            "animEndType": 1
          },
          "actorIndex": 0
        },
        "emotionActData": {
          "emotionDesc": {
            "browsTrackInfo": {},
            "eyesTrackInfo": {},
            "mouthTrackInfo": {}
          },
          "mEmotionDesc": {
            "browsTrackInfo": {},
            "eyesTrackInfo": {},
            "mouthTrackInfo": {}
          },
          "actorIndex": 0
        },
        "lookAtActData": {
          "lookAtDescriptor": {},
          "actorIndex": 0
        },
        "eyeLookAtActData": {
          "lookAtDescriptor": {},
          "actorIndex": 0
        },
        "turnToActData": {
          "actorIndex": 0
        },
        "actions": [],
        "actionGroups": [],
        "$type": "Beyond.Gameplay.DTTrunkNodeData"
      },
      "additionalWidth": 207.0,
      "_position": {
        "x": 600.0,
        "y": 200.0
      },
      "$type": "Beyond.Gameplay.DialogTreeTrunkNode",
      "$id": "1"
    },
    {
      "_actorNodeData": {
        "mfTrunkActionData": {
          "exUIDescriptor": {
            "_disableClickTime": 1.0
          },
          "_trunkId": "dlg_e2m7_8_003",
          "useLipSync": true,
          "voiceConfig": {},
          "microExpressionDesc": {},
          "actorIndex": 2,
          "duration": -1.0,
          "actionEnum": 307
        },
        "camActData": {
          "camDescriptor": {
            "modeNum": 3,
            "posName": "3_1_2_1",
            "slotNum": 2,
            "modeId": "1v2_Medium_Shot_S_low",
            "pos": {
              "x": 2.049,
              "y": 0.957,
              "z": 1.162
            },
            "rot": {
              "x": 349.6,
              "y": 244.9,
              "z": 4.643983e-05
            },
            "fov": 11.4
          },
          "mCamDescriptor": {},
          "actorIndex": 2,
          "delay": 0.0,
          "actionEnum": 51
        },
        "teleportAllEntityActData": {
          "actorPosList": []
        },
        "_showNpcs": [],
        "_hideNpcs": [],
        "_actorIndex": 2,
        "animActData": {
          "anim": {
            "fadeIn": 0.2,
            "montageDesc": {
              "montageKeyTag": {
                "tagName": "Montage/NPC/Humanoid/Girl/Chen/think1",
                "tagId": -1926115734
              },
              "montageFadeInTransitionInfo": {
                "bIsFixedTransitionTime": true,
                "fixedTransitionDuration": 0.5
              },
              "montageOverrideEntryTransitionInfo": []
            },
            "maleMontageOverrideDesc": {}
          },
          "actorIndex": 2
        },
        "emotionActData": {
          "emotionDesc": {
            "bPlayEmotion": true,
            "emotionTag": {
              "tagName": "FacialMorph/Emotion/worrieda",
              "tagId": 212718908
            },
            "browsTrackInfo": {},
            "eyesTrackInfo": {},
            "mouthTrackInfo": {}
          },
          "mEmotionDesc": {
            "browsTrackInfo": {},
            "eyesTrackInfo": {},
            "mouthTrackInfo": {}
          },
          "actorIndex": 2
        },
        "lookAtActData": {
          "lookAtDescriptor": {},
          "actorIndex": 2
        },
        "eyeLookAtActData": {
          "lookAtDescriptor": {},
          "actorIndex": 2
        },
        "turnToActData": {
          "actorIndex": 2
        },
        "actions": [],
        "actionGroups": [],
        "$type": "Beyond.Gameplay.DTTrunkNodeData"
      },
      "additionalWidth": 207.0,
      "_position": {
        "x": 1000.0,
        "y": 200.0
      },
      "$type": "Beyond.Gameplay.DialogTreeTrunkNode",
      "$id": "2"
    },
    {
      "_normalOptions": [
        {
          "_optionId": "option_dlg_e2m7_8_1_001",
          "logicId": 157
        }
      ],
      "additionalWidth": 139.0,
      "_position": {
        "x": 1480.0,
        "y": 260.0
      },
      "$type": "Beyond.Gameplay.DialogTreeOptionNode",
      "$id": "3"
    },
    {
      "_transitionData": {
        "_actionGroups": [
          {
            "duration": 2.0,
            "actions": [
              {
                "anim": {
                  "bodyAnim": "",
                  "upperBodyAnim": "",
                  "faceAnim": "",
                  "mouthAnim": "",
                  "montageDesc": {
                    "montageKeyTag": {
                      "tagName": "Montage/NPC/Virtual/idea_nod",
                      "tagId": 9506805
                    },
                    "montageBodyMask": 5,
                    "montageOverrideEntryTransitionInfo": [],
                    "changeMontageState": true,
                    "stateMontage": 0
                  },
                  "maleMontageOverrideDesc": {}
                },
                "actorIndex": 0,
                "$type": "Beyond.Gameplay.DialogAnimActData"
              }
            ]
          }
        ],
        "actions": []
      },
      "additionalWidth": 26.0,
      "_position": {
        "x": 1668.0,
        "y": 444.0
      },
      "$type": "Beyond.Gameplay.DialogTransitionNode",
      "$id": "4"
    },
    {
      "_actorNodeData": {
        "mfTrunkActionData": {
          "exUIDescriptor": {
            "_disableClickTime": 1.0
          },
          "_trunkId": "dlg_e2m7_8_004",
          "useLipSync": true,
          "voiceConfig": {},
          "microExpressionDesc": {},
          "actorIndex": 1,
          "duration": -1.0,
          "actionEnum": 307
        },
        "camActData": {
          "camDescriptor": {
            "modeNum": -1,
            "posName": "3_1_2_1",
            "slotNum": 1,
            "modeId": "1v2_panorama_S",
            "camType": 2,
            "pos": {
              "x": 2.84,
              "y": 1.521,
              "z": 3.723
            },
            "rot": {
              "x": 4.990023,
              "y": 226.4,
              "z": 6.856174e-06
            },
            "fov": 20.0
          },
          "mCamDescriptor": {
            "modeNum": -1,
            "camType": 2
          },
          "actorIndex": 1,
          "delay": 0.0,
          "actionEnum": 51
        },
        "teleportAllEntityActData": {
          "actorPosList": []
        },
        "_showNpcs": [],
        "_hideNpcs": [],
        "_actorIndex": 1,
        "animActData": {
          "anim": {
            "fadeIn": 0.2,
            "montageDesc": {
              "montageKeyTag": {
                "tagName": "Montage/NPC/Humanoid/Girl/Pelica/introduction2",
                "tagId": 64758544
              },
              "montageFadeInTransitionInfo": {
                "bIsFixedTransitionTime": true,
                "fixedTransitionDuration": 0.5
              },
              "montageOverrideEntryTransitionInfo": [],
              "montagePlaySpeed": 0.4
            },
            "maleMontageOverrideDesc": {}
          },
          "actorIndex": 1
        },
        "emotionActData": {
          "emotionDesc": {
            "bPlayEmotion": true,
            "emotionTag": {
              "tagName": "FacialMorph/Emotion/worrieda",
              "tagId": 212718908
            },
            "browsTrackInfo": {},
            "eyesTrackInfo": {},
            "mouthTrackInfo": {}
          },
          "mEmotionDesc": {
            "browsTrackInfo": {},
            "eyesTrackInfo": {},
            "mouthTrackInfo": {}
          },
          "actorIndex": 1
        },
        "lookAtActData": {
          "lookAtDescriptor": {},
          "actorIndex": 1
        },
        "eyeLookAtActData": {
          "lookAtDescriptor": {},
          "actorIndex": 1
        },
        "turnToActData": {
          "actorIndex": 1
        },
        "actions": [],
        "actionGroups": [],
        "$type": "Beyond.Gameplay.DTTrunkNodeData"
      },
      "additionalWidth": 207.0,
      "_position": {
        "x": 1880.0,
        "y": 200.0
      },
      "$type": "Beyond.Gameplay.DialogTreeTrunkNode",
      "$id": "5"
    },
    {
      "_actorNodeData": {
        "mfTrunkActionData": {
          "exUIDescriptor": {
            "_disableClickTime": 1.0
          },
          "_trunkId": "dlg_e2m7_8_005",
          "useLipSync": true,
          "voiceConfig": {},
          "microExpressionDesc": {},
          "actorIndex": 1,
          "duration": -1.0,
          "actionEnum": 307
        },
        "camActData": {
          "camDescriptor": {
            "modeNum": 3,
            "posName": "3_1_2_1",
            "slotNum": 1,
            "modeId": "1v2_Medium_Shot_S_low",
            "pos": {
              "x": 2.049,
              "y": 0.957,
              "z": 1.162
            },
            "rot": {
              "x": 349.6,
              "y": 244.9,
              "z": 4.643983e-05
            },
            "fov": 11.4
          },
          "mCamDescriptor": {},
          "actorIndex": 1,
          "delay": 0.0,
          "actionEnum": 51
        },
        "teleportAllEntityActData": {
          "actorPosList": []
        },
        "_showNpcs": [],
        "_hideNpcs": [],
        "_actorIndex": 1,
        "animActData": {
          "anim": {
            "fadeIn": 0.2,
            "montageDesc": {
              "montageKeyTag": {
                "tagName": "Montage/NPC/Humanoid/Girl/Pelica/introduction2",
                "tagId": 64758544
              },
              "montageOverrideEntryTransitionInfo": [],
              "changeMontageState": true,
              "stateMontage": 0
            },
            "maleMontageOverrideDesc": {}
          },
          "actorIndex": 1
        },
        "emotionActData": {
          "emotionDesc": {
            "browsTrackInfo": {},
            "eyesTrackInfo": {},
            "mouthTrackInfo": {}
          },
          "mEmotionDesc": {
            "browsTrackInfo": {},
            "eyesTrackInfo": {},
            "mouthTrackInfo": {}
          },
          "actorIndex": 1
        },
        "lookAtActData": {
          "lookAtDescriptor": {},
          "actorIndex": 1
        },
        "eyeLookAtActData": {
          "lookAtDescriptor": {},
          "actorIndex": 1
        },
        "turnToActData": {
          "actorIndex": 1
        },
        "actions": [],
        "actionGroups": [],
        "$type": "Beyond.Gameplay.DTTrunkNodeData"
      },
      "additionalWidth": 207.0,
      "_position": {
        "x": 2280.0,
        "y": 200.0
      },
      "$type": "Beyond.Gameplay.DialogTreeTrunkNode",
      "$id": "6"
    },
    {
      "additionalWidth": 214.0,
      "_position": {
        "x": 2880.0,
        "y": 200.0
      },
      "$type": "Beyond.Gameplay.DialogTreeFinishNode",
      "$id": "7"
    },
    {
      "_actorNodeData": {
        "_actorIndex": 0,
        "animActData": {
          "anim": {
            "bodyAnim": "",
            "upperBodyAnim": "",
            "faceAnim": "",
            "mouthAnim": "",
            "fadeIn": 0.2,
            "montageDesc": {
              "montageKeyTag": {
                "tagName": "Montage/NPC/Virtual/walk_s",
                "tagId": -320873648
              },
              "montageFadeInTransitionInfo": {
                "bIsFixedTransitionTime": true,
                "fixedTime": 0.5,
                "fixedTransitionDuration": 0.2
              },
              "montageOverrideEntryTransitionInfo": [],
              "stateMontage": 2,
              "bApplyRootMotion": true
            }
          },
          "actorIndex": 0
        },
        "emotionActData": {
          "emotionDesc": {
            "browsTrackInfo": {},
            "eyesTrackInfo": {},
            "mouthTrackInfo": {}
          },
          "mEmotionDesc": {
            "browsTrackInfo": {},
            "eyesTrackInfo": {},
            "mouthTrackInfo": {}
          },
          "actorIndex": 0
        },
        "lookAtActData": {
          "lookAtDescriptor": {},
          "actorIndex": 0
        },
        "eyeLookAtActData": {
          "lookAtDescriptor": {},
          "actorIndex": 0
        },
        "turnToActData": {
          "actorIndex": 0
        },
        "actions": [],
        "actionGroups": [],
        "$type": "Beyond.Gameplay.DTExActorNodeData"
      },
      "additionalWidth": 26.0,
      "_position": {
        "x": 266.0,
        "y": 508.0
      },
      "$type": "Beyond.Gameplay.DialogTreeExActorNode",
      "$id": "8"
    },
    {
      "_actionData": {
        "summaryId": "summary_e2m7_8_001",
        "$type": "Beyond.Gameplay.DialogSummaryActData"
      },
      "additionalWidth": 3.0,
      "_position": {
        "x": 191.0,
        "y": 374.0
      },
      "$type": "Beyond.Gameplay.DialogTreeExSummaryNode",
      "$id": "9"
    },
    {
      "_transitionData": {
        "_actionGroups": [
          {
            "duration": 4.8,
            "actions": [
              {
                "camDescriptor": {
                  "modeNum": -1,
                  "camType": 2,
                  "pos": {
                    "x": 28.71,
                    "y": 29.29,
                    "z": 8.03
                  },
                  "rot": {
                    "x": 34.2,
                    "y": 241.5255,
                    "z": 2.683912e-05
                  },
                  "fov": 30.0,
                  "useTranslation": true,
                  "translationPos": {
                    "x": 30.17,
                    "y": 29.29,
                    "z": 3.53
                  },
                  "translationRot": {
                    "x": 33.20001,
                    "y": 247.7,
                    "z": 4.285375e-05
                  },
                  "translationTime": 7.5
                },
                "mCamDescriptor": {
                  "modeNum": -1,
                  "camType": 2
                },
                "duration": 0.1,
                "actionEnum": 51,
                "$type": "Beyond.Gameplay.DialogCamActData"
              },
              {
                "hideEffects": [],
                "showEffects": [
                  {
                    "effectIndex": 0,
                    "reset": true,
                    "position": {
                      "x": -15.21,
                      "y": -4.47,
                      "z": -14.17
                    },
                    "rotation": {
                      "y": 41.54
                    },
                    "scale": {
                      "x": 1.0,
                      "y": 1.0,
                      "z": 1.0
                    }
                  },
                  {
                    "effectIndex": 2,
                    "reset": true,
                    "position": {
                      "x": -15.21,
                      "y": -4.47,
                      "z": -14.17
                    },
                    "rotation": {
                      "y": 41.54
                    },
                    "scale": {
                      "x": 1.0,
                      "y": 1.0,
                      "z": 1.0
                    }
                  }
                ],
                "duration": 0.1,
                "$type": "Beyond.Gameplay.DialogEffectActionData"
              }
            ]
          },
          {
            "duration": 2.7,
            "actions": [
              {
                "hideEffects": [
                  2
                ],
                "showEffects": [],
                "duration": 0.1,
                "$type": "Beyond.Gameplay.DialogEffectActionData"
              }
            ]
          },
          {
            "duration": 5.0,
            "actions": [
              {
                "camDescriptor": {
                  "modeNum": -1,
                  "camType": 2,
                  "pos": {
                    "x": 80.27573,
                    "y": -29.6807,
                    "z": 235.0402
                  },
                  "rot": {
                    "x": 359.9022,
                    "y": 246.47,
                    "z": 7.703985e-06
                  },
                  "fov": 30.0,
                  "useTranslation": true,
                  "translationPos": {
                    "x": 77.49,
                    "y": -29.68,
                    "z": 233.83
                  },
                  "translationRot": {
                    "x": 359.9022,
                    "y": 246.47,
                    "z": 7.703985e-06
                  },
                  "translationTime": 5.0
                },
                "mCamDescriptor": {
                  "modeNum": -1,
                  "camType": 2
                },
                "duration": 0.1,
                "actionEnum": 51,
                "$type": "Beyond.Gameplay.DialogCamActData"
              },
              {
                "eventName": "action_e2m7_5",
                "duration": 0.1,
                "$type": "Beyond.Gameplay.DialogLevelEventActionData"
              }
            ]
          }
        ],
        "actions": []
      },
      "additionalWidth": 26.0,
      "_position": {
        "x": -80.0,
        "y": 220.0
      },
      "$type": "Beyond.Gameplay.DialogTransitionNode"
    }
  ],
  "connections": [
    {
      "_sourceNode": {
        "$ref": "0"
      },
      "_targetNode": {
        "$ref": "1"
      },
      "$type": "Beyond.Gameplay.DialogTreeConnection"
    },
    {
      "_sourceNode": {
        "$ref": "0"
      },
      "_targetNode": {
        "$ref": "8"
      },
      "$type": "Beyond.Gameplay.DialogTreeConnection"
    },
    {
      "_sourceNode": {
        "$ref": "0"
      },
      "_targetNode": {
        "$ref": "9"
      },
      "$type": "Beyond.Gameplay.DialogTreeConnection"
    },
    {
      "_sourceNode": {
        "$ref": "1"
      },
      "_targetNode": {
        "$ref": "2"
      },
      "$type": "Beyond.Gameplay.DialogTreeConnection"
    },
    {
      "_sourceNode": {
        "$ref": "2"
      },
      "_targetNode": {
        "$ref": "3"
      },
      "$type": "Beyond.Gameplay.DialogTreeConnection"
    },
    {
      "_sourceNode": {
        "$ref": "3"
      },
      "_targetNode": {
        "$ref": "4"
      },
      "$type": "Beyond.Gameplay.DialogTreeConnection"
    },
    {
      "_sourceNode": {
        "$ref": "4"
      },
      "_targetNode": {
        "$ref": "5"
      },
      "$type": "Beyond.Gameplay.DialogTreeConnection"
    },
    {
      "_sourceNode": {
        "$ref": "5"
      },
      "_targetNode": {
        "$ref": "6"
      },
      "$type": "Beyond.Gameplay.DialogTreeConnection"
    },
    {
      "_sourceNode": {
        "$ref": "6"
      },
      "_targetNode": {
        "$ref": "7"
      },
      "$type": "Beyond.Gameplay.DialogTreeConnection"
    }
  ],
  "canvasGroups": [],
  "localBlackboard": {
    "_variables": {}
  },
  "derivedData": {
    "_dialogType": 2,
    "beforeMaskBlendData": {},
    "afterMaskBlendData": {
      "fadeOutDuration": 0.0
    },
    "hideSquad": true,
    "interactText": {
      "key": "dlg_e2m7_8"
    },
    "rootPos": {
      "x": 262.21,
      "y": 67.79,
      "z": 561.48
    },
    "rootRot": {
      "y": 95.2
    },
    "hideFacBuildingDesc": {
      "showFacBuildingTypes": []
    },
    "voiceType": 4,
    "inAudioEvent": "au_music_dlg_exploring",
    "outAudioEvent": "au_music_dlg_exploring",
    "actors": [],
    "npcVisibleRuleType": 2,
    "npcBlackList": [],
    "npcWhiteList": [],
    "privateActors": [
      {
        "templateId": "npc_chr_0003_endminf",
        "lookAt": 1,
        "position": {
          "z": 1.86
        },
        "rotation": {
          "y": 180.0
        }
      },
      {
        "templateId": "npc_chr_0004_pelica",
        "lookAt": 0
      },
      {
        "templateId": "npc_chr_0005_chen",
        "lookAt": 0,
        "position": {
          "x": -0.77,
          "z": 0.13
        },
        "rotation": {
          "y": 28.1
        }
      }
    ],
    "exLights": [],
    "exEffects": [
      {
        "path": "P_map_lv006_angel_anchor_explosion_01"
      },
      {
        "path": "P_map_lv006_angel_anchor_explosionstore_01"
      },
      {
        "path": "P_map_lv006_angel_anchor_core_02"
      }
    ],
    "tmpGameObjects": [],
    "$type": "Beyond.Gameplay.DialogTreeData"
  }
}